dfns/__init__.py
dfns/tools.py
dfns-1.0.1.dist-info/METADATA
dfns-1.0.1.dist-info/WHEEL
dfns-1.0.1.dist-info/top_level.txt
dfns-1.0.1.dist-info/RECORD
