Metadata-Version: 2.1
Name: dfns
Version: 1.0.1
Summary: Cloud data pipeline organization and automation library with encryption services.
Home-page: https://dfns.technology
Author: Diego Nuñez Sabbagh
Author-email: diego@dfns.technology
License: MIT
Platform: UNKNOWN
Classifier: Intended Audience :: Developers
Classifier: License :: OSI Approved :: MIT License
Classifier: Programming Language :: Python
Classifier: Programming Language :: Python :: 3
Classifier: Programming Language :: Python :: 3.6
Classifier: Programming Language :: Python :: 3.7
Classifier: Programming Language :: Python :: 3.8
Classifier: Programming Language :: Python :: 3.9
Classifier: Operating System :: OS Independent
Requires-Dist: pandas
Requires-Dist: pandasql
